topsis/__init__.py
topsis/topsis.py
topsis_python_souravdlboy-2.8.dist-info/LICENSE
topsis_python_souravdlboy-2.8.dist-info/METADATA
topsis_python_souravdlboy-2.8.dist-info/WHEEL
topsis_python_souravdlboy-2.8.dist-info/top_level.txt
topsis_python_souravdlboy-2.8.dist-info/RECORD
